{
  "modules": {
    "byIdentifier": {
      "multi node_modules/next/dist/client/next": 0
    },
    "usedIds": {
      "0": 0
    }
  },
  "chunks": {
    "byName": {
      "commons": 0,
      "static/runtime/webpack.js": 1,
      "static/runtime/main.js": 2,
      "static\\tMswQ6AYCzgYyJSP40hY_\\pages\\_app.js": 3,
      "static\\tMswQ6AYCzgYyJSP40hY_\\pages\\_error.js": 4,
      "static\\tMswQ6AYCzgYyJSP40hY_\\pages\\about.js": 5,
      "static\\tMswQ6AYCzgYyJSP40hY_\\pages\\index.js": 6
    },
    "bySource": {},
    "usedIds": [
      0,
      1,
      2,
      3,
      4,
      5,
      6
    ]
  }
}